{
    "jukeboxes" : [
        {
            "name" : "local",
            "isdefault" : true,
            "host" : "http://192.168.1.201:5000"
        },
        {
            "name" : "one",
            "isdefault" : false,
            "host" : "http://192.168.1.200:5000"
        }
    ],
    "playerrequestendpoint" : "/api/Player/Request",
    "playercontrolrequestendpoint" : "/api/Player/Control",
    "conversationstartedendpoint" : "/api/Player/ConversationStarted",
    "conversationfinishedendpoint" : "/api/Player/ConversationFinished"
}